ldit/__init__.py
ldit/ldit.py
ldit-0.0.1.data/scripts/ldit
ldit-0.0.1.dist-info/LICENSE
ldit-0.0.1.dist-info/METADATA
ldit-0.0.1.dist-info/WHEEL
ldit-0.0.1.dist-info/top_level.txt
ldit-0.0.1.dist-info/RECORD
