Metadata-Version: 2.1
Name: ldit
Version: 0.0.1
Summary: List Docker hub Image Tags.
Home-page: https://github.com/geekpany/ldit
Author: pany
Author-email: pany@fedoraproject.org
License: UNKNOWN
Platform: UNKNOWN
Classifier: Programming Language :: Python :: 3
Classifier: License :: OSI Approved :: MIT License
Classifier: Operating System :: OS Independent
Requires-Dist: requests
